{
  "parent": "minecraft:recipes/root",
  "criteria": {
    "has_material": {
      "trigger": "minecraft:inventory_changed",
      "conditions": {
        "items": [
          {
            "items": [
              "minecraft:diamond"
            ]
          }
        ]
      }
    },
    "has_recipe": {
      "trigger": "minecraft:recipe_unlocked",
      "conditions": {
        "recipe": "ironladders:wood_diamond_upgrade"
      }
    }
  },
  "requirements": [
    [
      "has_material",
      "has_recipe"
    ]
  ],
  "rewards": {
    "recipes": [
      "ironladders:wood_diamond_upgrade"
    ]
  }
}